deneb/__init__.py
deneb/__version__.py
deneb/correlation_matrix.py
deneb/lineplot.py
deneb/pairplot.py
deneb/themes.py
deneb/utils.py
deneb-1.0.1.dist-info/LICENSE
deneb-1.0.1.dist-info/METADATA
deneb-1.0.1.dist-info/WHEEL
deneb-1.0.1.dist-info/top_level.txt
deneb-1.0.1.dist-info/RECORD
