Metadata-Version: 2.1
Name: deneb
Version: 1.0.1
Summary: Visualization library build on top of Altair and Vega
Home-page: https://github.com/sbi-benchmark/deneb
Author: Jan-Matthis Lueckmann
Author-email: mail@jan-matthis.de
License: MIT
Platform: UNKNOWN
Classifier: License :: OSI Approved :: MIT License
Classifier: Intended Audience :: Science/Research
Classifier: Programming Language :: Python
Classifier: Programming Language :: Python :: 3
Classifier: Programming Language :: Python :: 3.6
Classifier: Programming Language :: Python :: Implementation :: PyPy
Requires-Python: >=3.6.0
Requires-Dist: altair
Requires-Dist: altair-saver
Requires-Dist: flatlatex
Requires-Dist: mergedeep
Requires-Dist: vega-datasets
Provides-Extra: dev
Requires-Dist: autoflake ; extra == 'dev'
Requires-Dist: black ; extra == 'dev'
Requires-Dist: flake8 ; extra == 'dev'
Requires-Dist: ipdb ; extra == 'dev'
Requires-Dist: isort ; extra == 'dev'
Requires-Dist: pytest ; extra == 'dev'
